{"narrative":1,"narrativeName":"freezing-europe","path":"export/content/1/backgrounds/sanctions-tableau-isolation.json","identifier":"sanctions-tableau-isolation-12-12","order":null,"component":"BarChart","keywords":"(изоляц,изолир + росс)xr","data":"ok","events":"sanctions-general","headlines":"ok","description":"The graph depicts the frequency of headlines mention in relevant Russian-language media. It uses regex expressions for requesting the words \"isolation\", \"Russia\" in the Tableau worksheet. Timeframe: 01.01.2022 - 31.07.2022. Data source: GDELT.","chart_title":"Frequency of headlines mentioning the \"isolation\" marker","uuid":"5593642a-4811-11ed-9d91-7730c92ea146","stepstart":12,"stepend":12,"name":"sanctions-tableau-isolation"}